announcements/__init__.py
announcements/admin.py
announcements/context_processors.py
announcements/defaults.py
announcements/models.py
announcements/urls.py
announcements/views.py
announcements/templates/announcements/announcement.html
announcements/templates/announcements/announcements.html
announcements/templatetags/__init__.py
announcements/templatetags/announcements_tags.py
django_simple_announcements-0.2.2.dist-info/DESCRIPTION.rst
django_simple_announcements-0.2.2.dist-info/METADATA
django_simple_announcements-0.2.2.dist-info/RECORD
django_simple_announcements-0.2.2.dist-info/WHEEL
django_simple_announcements-0.2.2.dist-info/metadata.json
django_simple_announcements-0.2.2.dist-info/top_level.txt
