Metadata-Version: 2.0
Name: django-simple-announcements
Version: 0.2.2
Summary: Basic site-wide announcements for your Django project.
Home-page: https://github.com/craigds/django-simple-announcements/
Author: Craig de Stigter
Author-email: craig.ds@gmail.com
License: UNKNOWN
Platform: UNKNOWN
Classifier: Development Status :: 4 - Beta
Classifier: Environment :: Web Environment
Classifier: Framework :: Django
Classifier: Intended Audience :: Developers
Classifier: License :: OSI Approved :: BSD License
Classifier: Operating System :: OS Independent
Classifier: Programming Language :: Python
Classifier: Topic :: Utilities
